{
  "extractor": "docling",
  "confidence": 0.9500000000000001,
  "character_count": 3416,
  "extraction_metadata": {
    "extraction_time": 11.251647233963013,
    "pages": 3,
    "tables": [
      "Table 1"
    ],
    "sections": [
      "Aufstellung \u00fcber Kundenfinanzinstrumente per 30.09.2023",
      "Aufstellung \u00fcber Kundenfinanzinstrumente per 30.09.2023",
      "Aufstellung \u00fcber Kundenfinanzinstrumente per 30.09.2023"
    ],
    "has_tables": true,
    "has_formulas": false,
    "document_type": "invoice"
  },
  "file_size": 3454
}